[
	{
	  "username": "veniam",
	  "email": "Mx8E3H4TVr@rNaCqgnQxp.sz",
	  "passwordHash": "amet cupidatat",
	  "roles": [
		"ADMIN",
		"ADMIN",
		"READER"
	  ]
	},
	{
	  "username": "qui quis",
	  "email": "fUwpRV@OXBlMuRHkVenLqQODZe.sw",
	  "passwordHash": "pariatur",
	  "roles": [
		"ADMIN",
		"ADMIN"
	  ]
	},
	{
	  "username": "non ut anim lab",
	  "email": "6PusbyGRH2Ak@VSUEyNTNtjezEaYIMPlyNUZwfaupHWfu.ugqy",
	  "passwordHash": "ipsum dolor commodo qui",
	  "roles": [
		"READER",
		"ADMIN"
	  ]
	},
	{
	  "username": "labore",
	  "email": "0gEbUW@MfqMXz.cq",
	  "passwordHash": "ad nostrud occaecat est",
	  "roles": [
		"READER",
		"WRITER"
	  ]
	},
	{
	  "username": "ut cupidatat nostrud",
	  "email": "FRFzuKm@aLqQGNMQZfeUgsSumWMEZhLDdYpsC.jp",
	  "passwordHash": "incid",
	  "roles": [
		"ADMIN",
		"READER",
		"REVIEWER",
		"READER"
	  ]
	},
	{
	  "username": "exercitation esse amet",
	  "email": "1pU0zUZ-k@hezSkqfmFUiigBVHwTitWqyGA.ywbl",
	  "passwordHash": "laboris velit",
	  "roles": [
		"REVIEWER",
		"REVIEWER",
		"REVIEWER",
		"ADMIN",
		"WRITER"
	  ]
	},
	{
	  "username": "dolore sit in",
	  "email": "58dwIjwBW2J0@xlfSAvwlvGjdOixrJjaHGE.fy",
	  "passwordHash": "culpa velit do",
	  "roles": [
		"WRITER",
		"REVIEWER",
		"REVIEWER",
		"READER",
		"READER"
	  ]
	},
	{
	  "username": "officia voluptate",
	  "email": "yS5KqfK@LoPxybADtkdYII.gfbd",
	  "passwordHash": "Duis",
	  "roles": [
		"REVIEWER",
		"WRITER",
		"READER",
		"WRITER",
		"WRITER"
	  ]
	},
	{
	  "username": "voluptate dolor magna",
	  "email": "pQu@RSpmnkzZDAVM.exw",
	  "passwordHash": "culpa dolore",
	  "roles": [
		"REVIEWER"
	  ]
	},
	{
	  "username": "ut labore elit",
	  "email": "71ja1WQ-3Tx1@fCaoGZmGTzmuHU.vpw",
	  "passwordHash": "irure veniam ad",
	  "roles": [
		"READER",
		"ADMIN"
	  ]
	},
	{
	  "username": "laboris consectetur",
	  "email": "exsaKEJz@TvqfOUMvpQrzqtmqfzyNIpnrR.xxcz",
	  "passwordHash": "nostrud Lorem officia anim",
	  "roles": [
		"READER",
		"WRITER"
	  ]
	},
	{
	  "username": "elit Ut",
	  "email": "0H5Rc4kTg@IvtaOYIjHHhifhPeNtAcFAJXCj.ld",
	  "passwordHash": "esse amet aut",
	  "roles": [
		"READER",
		"REVIEWER",
		"READER",
		"READER"
	  ]
	},
	{
	  "username": "dolore ad do",
	  "email": "IMtd9WWo1UV@VdyAuxGJbN.wxw",
	  "passwordHash": "quis velit qui",
	  "roles": [
		"REVIEWER",
		"REVIEWER",
		"READER",
		"WRITER",
		"REVIEWER"
	  ]
	},
	{
	  "username": "Lorem ipsum pariatur velit",
	  "email": "7PEZMgqZIQFTS3@ViTkZMjHz.zz",
	  "passwordHash": "nulla",
	  "roles": [
		"ADMIN",
		"WRITER"
	  ]
	},
	{
	  "username": "non",
	  "email": "4GfbWIWBbbUKTIT@OHVHuGHfSuz.clq",
	  "passwordHash": "incididunt Duis eu",
	  "roles": [
		"ADMIN",
		"REVIEWER",
		"READER",
		"READER"
	  ]
	},
	{
	  "username": "commodo sed",
	  "email": "bb-7HMz4@R.jmh",
	  "passwordHash": "dolor ut tempor",
	  "roles": [
		"READER",
		"WRITER",
		"ADMIN"
	  ]
	},
	{
	  "username": "reprehenderit eiusmod elit",
	  "email": "8aQ-id-1VDlG@LQRVIXJGkdAejlNrBUniNeQYvul.lb",
	  "passwordHash": "proident occaecat commodo ad",
	  "roles": [
		"ADMIN",
		"ADMIN",
		"REVIEWER",
		"WRITER",
		"REVIEWER"
	  ]
	},
	{
	  "username": "do ad quis ex",
	  "email": "4CAq0jj@tKF.ggs",
	  "passwordHash": "velit incididunt aute",
	  "roles": [
		"ADMIN",
		"ADMIN",
		"ADMIN",
		"ADMIN",
		"REVIEWER"
	  ]
	},
	{
	  "username": "elit est dolor officia et",
	  "email": "yJGFIkaQiQUWg6@fDrNKLHqzhHoXWffXocxAHuYf.yx",
	  "passwordHash": "in ad mollit",
	  "roles": [
		"READER",
		"REVIEWER",
		"READER"
	  ]
	},
	{
	  "username": "nulla Excepteur sint",
	  "email": "04aqrJeaubKCkVN@hEoTydTMBMrMfhv.gula",
	  "passwordHash": "dolor ",
	  "roles": [
		"REVIEWER",
		"ADMIN",
		"REVIEWER"
	  ]
	},
	{
	  "username": "non veniam proident Lorem aliqua",
	  "email": "zTn8fD334j7k@jIH.yd",
	  "passwordHash": "adipisicing culpa nisi",
	  "roles": [
		"READER",
		"ADMIN",
		"READER",
		"ADMIN",
		"WRITER"
	  ]
	},
	{
	  "username": "enim id ",
	  "email": "6c5gm@Y.ulb",
	  "passwordHash": "officia labore mollit aliquip cupidatat",
	  "roles": [
		"READER",
		"WRITER",
		"WRITER",
		"ADMIN"
	  ]
	},
	{
	  "username": "tempor laboris est qui",
	  "email": "7m3@uhwvxkyNMqPfZUTuMv.gngj",
	  "passwordHash": "ipsum reprehenderit",
	  "roles": [
		"WRITER",
		"REVIEWER"
	  ]
	},
	{
	  "username": "cupidatat sint magna",
	  "email": "RBw@biKSTIDiZGNMYcYiRi.zx",
	  "passwordHash": "tempor",
	  "roles": [
		"ADMIN",
		"WRITER",
		"WRITER"
	  ]
	},
	{
	  "username": "labo",
	  "email": "JAfJ@EBvyGzERKN.mguu",
	  "passwordHash": "aliqua veniam magna labore nisi",
	  "roles": [
		"READER",
		"WRITER",
		"READER",
		"READER"
	  ]
	},
	{
	  "username": "aute ullamco esse",
	  "email": "KrWiE8cX@Xvw.ks",
	  "passwordHash": "minim fugiat",
	  "roles": [
		"REVIEWER",
		"REVIEWER",
		"REVIEWER",
		"WRITER"
	  ]
	},
	{
	  "username": "culpa",
	  "email": "jEEqOnEnw35NpuV@vbUgxeqokCETHTOsTVGnQNNqKl.cz",
	  "passwordHash": "reprehenderit eiusmod",
	  "roles": [
		"READER",
		"READER",
		"READER",
		"ADMIN",
		"READER"
	  ]
	},
	{
	  "username": "in ad incididunt cillum",
	  "email": "UXevcxngvZWK@MG.jnk",
	  "passwordHash": "in ven",
	  "roles": [
		"WRITER"
	  ]
	},
	{
	  "username": "ea",
	  "email": "RDodM5rYSsmf@QHur.cr",
	  "passwordHash": "Ut",
	  "roles": [
		"REVIEWER",
		"READER",
		"WRITER",
		"ADMIN"
	  ]
	},
	{
	  "username": "reprehenderit sunt dolor velit",
	  "email": "WXAOU2nGo1KoNpk@lCjzcvATdYxBFhyrJMxZOnNh.hquy",
	  "passwordHash": "officia elit Ut deserunt",
	  "roles": [
		"ADMIN",
		"ADMIN",
		"WRITER",
		"WRITER"
	  ]
	},
	{
	  "username": "officia sit ipsum in",
	  "email": "bNxYjbxh@UfKzpjshjBAwuMptFjBcauL.jwc",
	  "passwordHash": "qui anim do dolor et",
	  "roles": [
		"READER",
		"REVIEWER",
		"REVIEWER",
		"WRITER"
	  ]
	},
	{
	  "username": "Duis officia rep",
	  "email": "FmDCep47HF6zT@FmNSNdJPswGoodMNLhT.dbu",
	  "passwordHash": "incididunt enim non",
	  "roles": [
		"WRITER",
		"REVIEWER",
		"READER"
	  ]
	},
	{
	  "username": "eu eiusmod",
	  "email": "bquif6eDGcJ8B@KDTRIiSsbdwqxpEIxCkAdrF.hyqj",
	  "passwordHash": "Excepteur sed",
	  "roles": [
		"WRITER",
		"REVIEWER",
		"WRITER"
	  ]
	},
	{
	  "username": "elit velit",
	  "email": "xP-uLWelP38@FIsySExISLsVPBVaHMzoxmR.mi",
	  "passwordHash": "exercitation sint sit",
	  "roles": [
		"READER",
		"REVIEWER",
		"WRITER"
	  ]
	},
	{
	  "username": "amet",
	  "email": "cKpGLw9@OzOMQXrhnUDBWLUbCge.lrpd",
	  "passwordHash": "est laboris Excepteur",
	  "roles": [
		"READER",
		"ADMIN",
		"READER",
		"READER"
	  ]
	},
	{
	  "username": "deserunt qui laboris occaecat irure",
	  "email": "P57maeL@ovyOQQSjOQuWLCMOBdvqdTcJZhQ.cf",
	  "passwordHash": "ad aute dolore veniam",
	  "roles": [
		"READER",
		"WRITER",
		"READER"
	  ]
	},
	{
	  "username": "dolore",
	  "email": "guW1oWl@Ztym.lg",
	  "passwordHash": "exercitation",
	  "roles": [
		"ADMIN",
		"ADMIN"
	  ]
	},
	{
	  "username": "ipsum Duis sunt",
	  "email": "STcl@lactdT.gtw",
	  "passwordHash": "consectetur in",
	  "roles": [
		"REVIEWER",
		"REVIEWER",
		"REVIEWER"
	  ]
	},
	{
	  "username": "nisi quis dolore in",
	  "email": "82TVDHnvLd@OYiQFldE.jmko",
	  "passwordHash": "laborum aliqua",
	  "roles": [
		"REVIEWER",
		"REVIEWER"
	  ]
	},
	{
	  "username": "aute",
	  "email": "yXO-8OtI0LeAz3@ZoZpLXfHZSDUcBMZTNdfOAROhklPUPtJs.gcgl",
	  "passwordHash": "laborum elit",
	  "roles": [
		"ADMIN"
	  ]
	},
	{
	  "username": "laborum",
	  "email": "T4Oq-cWH7Iu@aXOGqxgmEZABdOvWsqniVv.uzcg",
	  "passwordHash": "aliqua esse Ut dolor",
	  "roles": [
		"REVIEWER",
		"ADMIN",
		"WRITER",
		"WRITER"
	  ]
	},
	{
	  "username": "nostrud",
	  "email": "N89n8ZxPGrY0Hu@JeIXqBoHpkJZQldqnYnYHiRonpyYF.uqh",
	  "passwordHash": "dolor ut",
	  "roles": [
		"REVIEWER",
		"REVIEWER"
	  ]
	},
	{
	  "username": "nisi commodo officia in",
	  "email": "r7CPTcwA@zAcwfGxV.wjd",
	  "passwordHash": "laboris",
	  "roles": [
		"ADMIN",
		"REVIEWER",
		"WRITER",
		"ADMIN"
	  ]
	},
	{
	  "username": "officia Excepteur",
	  "email": "iPrJQuyJxkWGN@DQmzQFiyfAnnPcnKDpuiGk.rj",
	  "passwordHash": "ex minim",
	  "roles": [
		"WRITER",
		"WRITER",
		"READER",
		"ADMIN"
	  ]
	},
	{
	  "username": "laborum do",
	  "email": "PowmxoWm@xBEWuzsXxsmKnsv.dl",
	  "passwordHash": "occaecat nostrud laboris velit Duis",
	  "roles": [
		"WRITER",
		"REVIEWER",
		"ADMIN"
	  ]
	},
	{
	  "username": "irure minim commodo dolore",
	  "email": "SJftl5cJy5@aaiivCaptsSG.fv",
	  "passwordHash": "irure ut",
	  "roles": [
		"WRITER",
		"ADMIN",
		"WRITER",
		"READER"
	  ]
	},
	{
	  "username": "Excepteur irur",
	  "email": "u1WaGnxA3eZ@mstGcWPjOHLNgQezCpfcECwAKYrGQsD.he",
	  "passwordHash": "l",
	  "roles": [
		"ADMIN",
		"WRITER",
		"ADMIN",
		"REVIEWER",
		"REVIEWER"
	  ]
	},
	{
	  "username": "et",
	  "email": "tnofPBE4B93V@XbZaoPgyWbRSfRxojIkhdcvJjpTcHn.opvo",
	  "passwordHash": "fugiat est",
	  "roles": [
		"REVIEWER",
		"WRITER"
	  ]
	},
	{
	  "username": "Lorem cupidatat elit in",
	  "email": "GfyE@mlAOsPUfHSNrApMpJij.jfs",
	  "passwordHash": "aliqua id",
	  "roles": [
		"ADMIN",
		"REVIEWER",
		"WRITER",
		"WRITER"
	  ]
	},
	{
	  "username": "labore commodo",
	  "email": "7uc@OOyyabDKv.sw",
	  "passwordHash": "cupidatat s",
	  "roles": [
		"REVIEWER",
		"WRITER",
		"WRITER"
	  ]
	},
	{
	  "username": "mollit ullamco",
	  "email": "Iw0@deNVpvOQWCss.kpf",
	  "passwordHash": "ipsum eu",
	  "roles": [
		"READER",
		"WRITER",
		"WRITER",
		"ADMIN"
	  ]
	},
	{
	  "username": "Duis eiusmod",
	  "email": "uicxoCY@wmWwJNvNd.co",
	  "passwordHash": "labore minim ea",
	  "roles": [
		"READER",
		"REVIEWER"
	  ]
	},
	{
	  "username": "ut enim dolore",
	  "email": "yEej@XTCTb.qh",
	  "passwordHash": "proident Lorem",
	  "roles": [
		"REVIEWER",
		"REVIEWER",
		"ADMIN",
		"READER"
	  ]
	},
	{
	  "username": "eiusmod nisi dolore esse",
	  "email": "m-Fr48IhOPerz@cFAJWOMNUeYGxjWBtAXUMKdWIcpFBsMqJ.qd",
	  "passwordHash": "commodo",
	  "roles": [
		"REVIEWER",
		"REVIEWER",
		"REVIEWER"
	  ]
	},
	{
	  "username": "nulla mollit enim commodo",
	  "email": "UeKXrm6ftKnPtaP@PeBsJFqKgIPutSb.jpwn",
	  "passwordHash": "occaecat aliquip esse",
	  "roles": [
		"REVIEWER",
		"ADMIN",
		"ADMIN"
	  ]
	},
	{
	  "username": "nulla minim eu culpa",
	  "email": "RVgLiR1ccKy12p@CPjGVBF.utdz",
	  "passwordHash": "aliquip",
	  "roles": [
		"WRITER",
		"WRITER",
		"WRITER",
		"ADMIN"
	  ]
	},
	{
	  "username": "incididunt esse eiusmod",
	  "email": "ub20AuBgv03@aXZyqWgcAXKgKgpoImQZpfwaXTk.esx",
	  "passwordHash": "non ut Lorem",
	  "roles": [
		"READER",
		"WRITER"
	  ]
	},
	{
	  "username": "cillum eu officia",
	  "email": "I4PjPcuI@MpVbJDqPqid.qarg",
	  "passwordHash": "mollit",
	  "roles": [
		"REVIEWER",
		"WRITER"
	  ]
	},
	{
	  "username": "Excepteur minim adipisicing ut quis",
	  "email": "0b30CgvBsy2k@aUFdITDzdSqNJClGvPBCxcfvQcpsT.tj",
	  "passwordHash": "esse quis adipisicing",
	  "roles": [
		"ADMIN",
		"READER",
		"READER",
		"ADMIN"
	  ]
	},
	{
	  "username": "incidid",
	  "email": "Td-fGN4@mEwskllkHlpZwJpLBYnppQksvCfsTu.yt",
	  "passwordHash": "dolore ut Lorem in",
	  "roles": [
		"REVIEWER",
		"ADMIN",
		"REVIEWER",
		"READER"
	  ]
	},
	{
	  "username": "quis velit veniam irure aute",
	  "email": "5BhfWDR6dsjb8@HwvXhwvlVwGtTThmkjBQFalkBL.nqre",
	  "passwordHash": "eiusmod pariatur cupidatat",
	  "roles": [
		"WRITER",
		"ADMIN",
		"READER",
		"READER",
		"REVIEWER"
	  ]
	},
	{
	  "username": "sed",
	  "email": "c7LQAaOXG@CEYLwNqugpdezxLD.cm",
	  "passwordHash": "cupidatat",
	  "roles": [
		"READER",
		"ADMIN",
		"READER"
	  ]
	},
	{
	  "username": "nulla non mollit amet exercitation",
	  "email": "knBZMSXiNxf@ZNrXPidkFSqZLWK.bcw",
	  "passwordHash": "reprehenderit ea sunt minim",
	  "roles": [
		"WRITER",
		"READER",
		"REVIEWER",
		"ADMIN"
	  ]
	},
	{
	  "username": "nisi dolore ad",
	  "email": "k4zHLv7Ixm39v@wkPReqVcMUKllNRBbGQoXBJEEkTH.tm",
	  "passwordHash": "elit",
	  "roles": [
		"READER",
		"ADMIN",
		"WRITER",
		"REVIEWER"
	  ]
	},
	{
	  "username": "null",
	  "email": "1UnXkI@yZQNeKECSSqXwDYvAKBSVcDEgFwK.uwos",
	  "passwordHash": "e",
	  "roles": [
		"WRITER",
		"WRITER"
	  ]
	},
	{
	  "username": "aliquip consequat",
	  "email": "31bMB3tucoxTwL@SukOuHWCFkb.rs",
	  "passwordHash": "culpa",
	  "roles": [
		"ADMIN",
		"ADMIN",
		"ADMIN",
		"ADMIN",
		"READER"
	  ]
	},
	{
	  "username": "deserunt consectetur culpa qui",
	  "email": "Y9i147DPj5XdNX@SitgajheNKGgzosgZwZhcWdAaAZP.tgq",
	  "passwordHash": "cillum fugiat",
	  "roles": [
		"ADMIN",
		"ADMIN",
		"ADMIN"
	  ]
	},
	{
	  "username": "et",
	  "email": "2GtZEdDbQW-BxF@NGwrkUCOBxzrGdjn.hu",
	  "passwordHash": "in",
	  "roles": [
		"ADMIN",
		"WRITER",
		"READER"
	  ]
	},
	{
	  "username": "officia proident magna com",
	  "email": "npzZ36@GdfeEhxuJAwRwIKSPiu.nqh",
	  "passwordHash": "in sed",
	  "roles": [
		"REVIEWER",
		"WRITER",
		"REVIEWER"
	  ]
	},
	{
	  "username": "proident adipisicing in",
	  "email": "fa4VbYXSa0VCiJ@sW.qk",
	  "passwordHash": "in adipisicing in do mollit",
	  "roles": [
		"WRITER"
	  ]
	},
	{
	  "username": "anim consectetur irure",
	  "email": "978Rg2PK-wRKPk@rOx.awsb",
	  "passwordHash": "commodo",
	  "roles": [
		"ADMIN",
		"ADMIN",
		"READER",
		"READER"
	  ]
	},
	{
	  "username": "tempor culpa",
	  "email": "LoWkx7@izRzADgJApShIlXDtqhzFJzUAGuMD.zl",
	  "passwordHash": "eiusmod ea id",
	  "roles": [
		"WRITER",
		"WRITER"
	  ]
	},
	{
	  "username": "pariatur sint Duis ullamco labore",
	  "email": "iUCOi-Clo@DfLfPinuPsKjLfTjO.mcxr",
	  "passwordHash": "do ipsum in",
	  "roles": [
		"REVIEWER",
		"ADMIN",
		"REVIEWER",
		"ADMIN",
		"ADMIN"
	  ]
	},
	{
	  "username": "tempor et anim nisi eiusmod",
	  "email": "PKZ8kY9Zkg7-rJ@KyRPBkQLfPrxRiAU.dsnj",
	  "passwordHash": "ex",
	  "roles": [
		"READER",
		"REVIEWER",
		"WRITER",
		"WRITER",
		"WRITER"
	  ]
	},
	{
	  "username": "proident reprehenderit",
	  "email": "3K5d4v2@E.qdlq",
	  "passwordHash": "in non",
	  "roles": [
		"ADMIN",
		"WRITER",
		"WRITER",
		"ADMIN"
	  ]
	},
	{
	  "username": "esse magna",
	  "email": "9qq7-uli-OmM1@xucyGRl.bm",
	  "passwordHash": "amet aute ex",
	  "roles": [
		"ADMIN",
		"READER",
		"REVIEWER",
		"ADMIN",
		"WRITER"
	  ]
	},
	{
	  "username": "eiusmod anim non nostrud",
	  "email": "aEJ42ZW3I4cP@sTjeMmMpyQlyzTgDLwIu.daz",
	  "passwordHash": "sunt ex Ut anim nostrud",
	  "roles": [
		"WRITER",
		"WRITER",
		"WRITER",
		"WRITER",
		"READER"
	  ]
	},
	{
	  "username": "anim elit",
	  "email": "K3auwxR@VnqdnNFohDLihdTs.hk",
	  "passwordHash": "eu ut qui",
	  "roles": [
		"ADMIN",
		"REVIEWER"
	  ]
	},
	{
	  "username": "in nisi",
	  "email": "23mvTTYfMtmNh5g@gfDWIRaNv.jb",
	  "passwordHash": "do consectetur fugiat",
	  "roles": [
		"REVIEWER",
		"ADMIN",
		"ADMIN",
		"READER",
		"REVIEWER"
	  ]
	},
	{
	  "username": "dolore",
	  "email": "mXK@iYuEItRni.sukp",
	  "passwordHash": "aliqua",
	  "roles": [
		"ADMIN",
		"WRITER",
		"ADMIN",
		"READER"
	  ]
	},
	{
	  "username": "nulla incididunt Excepteur",
	  "email": "mxycuJlZ6grF2cm@vzzBWsYwBanymEXnTbeR.rdhx",
	  "passwordHash": "ea ",
	  "roles": [
		"READER",
		"WRITER",
		"REVIEWER"
	  ]
	},
	{
	  "username": "sit veniam",
	  "email": "TR1JjwmweO@AcyIsBsSQmzwiBIPxefye.apyq",
	  "passwordHash": "qui",
	  "roles": [
		"ADMIN",
		"READER",
		"READER"
	  ]
	},
	{
	  "username": "ipsum non",
	  "email": "f1nWvzqmhN8@wVhQPZxVWXEVepPnKNl.qa",
	  "passwordHash": "sed eiusmod Ut",
	  "roles": [
		"ADMIN",
		"REVIEWER",
		"REVIEWER",
		"WRITER"
	  ]
	},
	{
	  "username": "ea dolore velit Ut nisi",
	  "email": "4ArR7031bqm@iPDbFOyHsgwylPWkbxfPNOaWw.rhi",
	  "passwordHash": "culpa occaecat irure ad",
	  "roles": [
		"REVIEWER",
		"READER",
		"WRITER"
	  ]
	},
	{
	  "username": "laboris dolore laborum",
	  "email": "FbkhFoKra@MSDFSkgujVaaAgGCZuX.olf",
	  "passwordHash": "irure laboris anim",
	  "roles": [
		"WRITER",
		"ADMIN",
		"ADMIN",
		"WRITER"
	  ]
	},
	{
	  "username": "cillum eu",
	  "email": "xIadEdw@DxGwFQgqzmPrU.jmkp",
	  "passwordHash": "deserunt ipsum in",
	  "roles": [
		"WRITER",
		"WRITER",
		"READER",
		"ADMIN"
	  ]
	},
	{
	  "username": "Ut Lorem in Duis cupidatat",
	  "email": "1xpg@xybCeqMxxDvmWfBiwDAHvHQRzXM.ph",
	  "passwordHash": "commodo ex voluptate",
	  "roles": [
		"REVIEWER",
		"ADMIN",
		"READER",
		"ADMIN"
	  ]
	},
	{
	  "username": "quis sit do magna",
	  "email": "NpZW@rFxVIYkAiccHswvzFdBDqxDDMXxX.uaq",
	  "passwordHash": "cupidatat sunt minim",
	  "roles": [
		"ADMIN",
		"REVIEWER",
		"ADMIN"
	  ]
	},
	{
	  "username": "nostrud eu",
	  "email": "emNyP@MA.vo",
	  "passwordHash": "ea voluptate nostrud mollit culpa",
	  "roles": [
		"WRITER",
		"REVIEWER",
		"ADMIN",
		"READER"
	  ]
	},
	{
	  "username": "nisi deserunt",
	  "email": "c4jDzBo0@gJOGWHUVbyNTggZZpolfftORyXv.li",
	  "passwordHash": "commodo eiusmod dolor",
	  "roles": [
		"READER",
		"REVIEWER",
		"WRITER",
		"REVIEWER"
	  ]
	},
	{
	  "username": "in",
	  "email": "VYIuwbHq@HBcJDj.mv",
	  "passwordHash": "aute irure nostrud minim",
	  "roles": [
		"REVIEWER",
		"ADMIN",
		"ADMIN"
	  ]
	},
	{
	  "username": "adipisicing quis",
	  "email": "053nF7a4g-2uRK5@bieqfTYnDQdUZ.fue",
	  "passwordHash": "adipisicing Duis id magna labore",
	  "roles": [
		"WRITER",
		"READER"
	  ]
	},
	{
	  "username": "sed",
	  "email": "OYoXYiZ@MQxzisiUXosHoXnQtRnFzVbkeMXp.trti",
	  "passwordHash": "ut consequat",
	  "roles": [
		"ADMIN",
		"REVIEWER"
	  ]
	},
	{
	  "username": "sint veniam ipsum cupidatat",
	  "email": "anUohLiRFGFch9j@ZsVOGEBZSttXZhzB.nv",
	  "passwordHash": "exercitation ad ex elit",
	  "roles": [
		"REVIEWER",
		"ADMIN",
		"ADMIN",
		"WRITER"
	  ]
	},
	{
	  "username": "aliqua mollit irure",
	  "email": "0yKHVArcN@Scnmj.gr",
	  "passwordHash": "laborum est",
	  "roles": [
		"REVIEWER",
		"ADMIN",
		"WRITER",
		"ADMIN"
	  ]
	},
	{
	  "username": "eiusmod reprehenderit aliquip aliqua sit",
	  "email": "j8CpX6@lXWgIPNqQLtlWSliyKiwyGUHoR.sgea",
	  "passwordHash": "Ut",
	  "roles": [
		"ADMIN",
		"READER"
	  ]
	},
	{
	  "username": "culpa irure dolor",
	  "email": "afurUn@xIRGDLnRJjbyXDsflB.dpy",
	  "passwordHash": "reprehenderit occaecat",
	  "roles": [
		"READER",
		"REVIEWER",
		"ADMIN"
	  ]
	},
	{
	  "username": "ad non nulla",
	  "email": "o8LoHYfHg@NETJyjqlpQdGAcfGqmrLwGy.lw",
	  "passwordHash": "ex sunt eiusmod dolor",
	  "roles": [
		"REVIEWER",
		"READER",
		"READER",
		"ADMIN"
	  ]
	},
	{
	  "username": "elit reprehenderit",
	  "email": "0lN@QtvObrYsitGBewuNHhZCEOBkGn.nbnw",
	  "passwordHash": "reprehenderit veniam in",
	  "roles": [
		"WRITER",
		"ADMIN"
	  ]
	},
	{
	  "username": "ea est labore",
	  "email": "4lKPBmE7x@wQqhWkKUd.bg",
	  "passwordHash": "eu in ut Ut",
	  "roles": [
		"ADMIN"
	  ]
	},
	{
	  "username": "reprehenderit eu in",
	  "email": "SchTS@fufbsFFU.nyox",
	  "passwordHash": "id in Excepteur mol",
	  "roles": [
		"READER",
		"READER"
	  ]
	},
	{
	  "username": "occaecat quis magna ex",
	  "email": "MZV-iUZLtj0Y@T.nun",
	  "passwordHash": "pari",
	  "roles": [
		"ADMIN",
		"ADMIN"
	  ]
	}
  ]
